data_mem.v
module data_mem (
    input wire clk,
    input wire write_en,
    input wire [2:0] mem_op,
    input wire [31:0] alu_result,
    input wire [31:0] write_data,
    output reg [31:0] read_data
);

    // Byte-addressable 1 KB memory
    reg [7:0] memory [0:1023];
    wire [31:0] addr = alu_result;

    always @(*) begin
        case (mem_op)
            3'b000:  // lw
                read_data = {memory[addr], memory[addr+1], memory[addr+2], memory[addr+3]};
            3'b010:  // lb (signed)
                read_data = {{24{memory[addr][7]}}, memory[addr]};
            3'b011:  // lbu (unsigned)
                read_data = {24'b0, memory[addr]};
            3'b101:  // lh (signed)
                read_data = {{16{memory[addr+1][7]}}, memory[addr+1], memory[addr]};
            3'b110:  // lhu (unsigned)
                read_data = {16'b0, memory[addr+1], memory[addr]};
            default:
                read_data = 32'b0;
        endcase
    end

    always @(posedge clk) begin
        if (write_en) begin
            case (mem_op)
                3'b001: begin // sw
                    memory[addr]   <= write_data[31:24];
                    memory[addr+1] <= write_data[23:16];
                    memory[addr+2] <= write_data[15:8];
                    memory[addr+3] <= write_data[7:0];
                end
                3'b100: begin // sb
                    memory[addr] <= write_data[7:0];
                end
                3'b111: begin // sh
                    memory[addr]   <= write_data[7:0];
                    memory[addr+1] <= write_data[15:8];
                end
            endcase
        end
    end

endmodule

alu.v
/* Implementation of 32-bit ALU with 4-bit control code */

module alu (
    input  wire [31:0] a, b,
    input  wire [3:0]  alu_op,
    output reg  [31:0] result,
    output reg zero
);

    wire [32:0] add_result = {1'b0, a} + {1'b0, b};
    wire [32:0] sub_result = {1'b0, a} - {1'b0, b};

    always @(*) begin
        case (alu_op)
            4'b0000: begin // AND
                result = a & b;
            end
            4'b0001: begin // OR
                result = a | b;
            end
            4'b0010: begin // ADD
                result = add_result[31:0];
            end
            4'b0110: begin // SUB
                result = sub_result[31:0];
            end
            4'b0111: begin // SLT (set if a < b)
                result = ($signed(a) < $signed(b)) ? 32'b1 : 32'b0;
            end
            default: begin
                result = 32'b0;
            end
        endcase

        zero = (result == 32'b0);
    end

endmodule

reg_file.v
module reg_file (
    input clk,
    input we3,
    input [4:0] ra1, ra2, wa3,
    input [31:0] wd3,
    output [31:0] rd1, rd2
);

reg [31:0] rf[31:0];

// three ported register file
// read two ports combinationally
// write third port on rising edge of clock
// register 0 hardwired to 0

always @(posedge clk) begin
    if (we3) rf[wa3] <= wd3;
end

assign rd1 = (ra1 != 0) ? rf[ra1]: 0;
assign rd2 = (ra2 != 0) ? rf[ra2]: 0;

endmodule

instr_mem.v
module instr_mem(
    input wire [31:0] addr,
    output wire [31:0] instr
);
    reg [31:0] memory [0:255];  // 1 KB of instruction space

    initial begin
        // Example: Load your instructions manually (machine code)

        // R-type: add $3, $1, $2
        memory[0] = 32'b000000_00001_00010_00011_00000_100000;

        // R-type: sub $4, $3, $1
        memory[1] = 32'b000000_00011_00001_00100_00000_100010;

        // I-type: addi $5, $0, 10
        memory[2] = 32'b001000_00000_00101_0000000000001010;

        // I-type: lw $6, 4($5)
        memory[3] = 32'b100011_00101_00110_0000000000000100;

        // I-type: sw $6, 8($5)
        memory[4] = 32'b101011_00101_00110_0000000000001000;

        // I-type: beq $1, $2, +2 (skip next 2 instructions if equal)
        memory[5] = 32'b000100_00001_00010_0000000000000010;

        // R-type: and $7, $1, $2 (this will be skipped if branch is taken)
        memory[6] = 32'b000000_00001_00010_00111_00000_100100;

        // J-type: j 0x00000003 (jump to instruction at address 0x0000000C)
        memory[7] = 32'b000010_00000000000000000000000011;

        // JAL: jal 0x00000004 (jump and link)
        memory[8] = 32'b000011_00000000000000000000000100;

        // LUI: lui $8, 0x1234 → $8 = 0x12340000
        memory[9] = 32'b001111_00000_01000_0001001000110100;

        // Fill rest with no-ops
        // integer i;
        // for (i = 10; i < 256; i = i + 1) begin
        //     memory[i] = 32'b000000_00000_00000_00000_00000_000000; // nop
        // end
    end

    assign instr = memory[addr[9:2]]; // Word aligned
    
endmodule

PC.v
module pc(
    input wire clk,
    input wire reset,
    input wire [31:0] next_pc,
    output reg [31:0] pc_out
);
    always @(posedge clk or posedge reset) begin
        if (reset)
            pc_out <= 32'b0;
        else
            pc_out <= next_pc;
    end
endmodule

ALUControl.v
module ALUControl (
    input wire [1:0] ALUOp,
    input wire [5:0] funct,
    input wire [5:0] op_code,

    output reg [3:0] code
);

always @(*) begin

    case (ALUOp)
    2'b00: code = 4'b0000;

    2'b01: code = 4'b0110;
    
    2'b10: begin
        case (funct)
        6'b100000: code = 4'b0010;
        6'b100010: code = 4'b0110;
        6'b100100: code = 4'b0000;
        6'b100101: code = 4'b0001;
        6'b101010: code = 4'b0111;

        default: code = 4'b1111;
        endcase
    end

    2'b11: begin
        case (op_code)
        6'b001100: code = 4'b0000; // andi
        6'b001101: code = 4'b0001; // ori
        6'b001010: code = 4'b0111; // slti
        default: code = 4'b1111;
    endcase
    end

    endcase

end
    
endmodule

Control_Unit.v
module control_unit (
    input wire [5:0] op_code, // inputs
    output reg RegDst, RegWrite, ALUSrc, MemtoReg,
                MemWrite, Branch, Jump, Lui, Jal,
    
    output reg [1:0] ALUOp
);

always @(*) begin
    
    case (op_code)
        6'b000000: begin // R-type
            RegDst = 1;
            RegWrite = 1;
            ALUSrc = 0;
            MemWrite = 0;
            MemtoReg = 0;
            Branch = 0;
            Jump = 0;
            Jal = 0;
            Lui = 0;
            ALUOp = 2'b10;
        end

        6'b100011: begin // lw
            RegDst = 0;
            RegWrite = 1;
            ALUSrc = 1;
            MemWrite = 0;
            MemtoReg = 1;
            Branch = 0;
            Jump = 0;
            Jal = 0;
            Lui = 0;
            ALUOp = 2'b00;
        end

        6'b101011: begin // sw
            RegDst = 1'b0; // don't care
            RegWrite = 0;
            ALUSrc = 1;
            MemWrite = 1;
            MemtoReg = 1'b0; // don't care
            Branch = 0;
            Jump = 0;
            Jal = 0;
            Lui = 0;
            ALUOp = 2'b00;            
        end

        6'b000100: begin // beq
            RegDst = 1'b0; // don't care
            RegWrite = 0;
            ALUSrc = 0;
            MemWrite = 0;
            MemtoReg = 1'b0; // don't care
            Branch = 1;
            Jump = 0;
            Jal = 0;
            Lui = 0;
            ALUOp = 2'b01;
        end

        6'b001000: begin // addi
            RegDst = 0;
            RegWrite = 1;
            ALUSrc = 1;
            MemWrite = 0;
            MemtoReg = 0;
            Branch = 0;
            Jump = 0;
            Jal = 0;
            Lui = 0;
            ALUOp = 2'b00;
        end

        6'b001100: begin // andi
            RegDst = 0;
            RegWrite = 1;
            ALUSrc = 1;
            MemWrite = 0;
            MemtoReg = 0;
            Branch = 0;
            Jump = 0;
            Jal = 0;
            Lui = 0;
            ALUOp = 2'b11;
        end

        6'b001101: begin // ori
            RegDst = 0;
            RegWrite = 1;
            ALUSrc = 1;
            MemWrite = 0;
            MemtoReg = 0;
            Branch = 0;
            Jump = 0;
            Jal = 0;
            Lui = 0;
            ALUOp = 2'b11;
        end

        6'b001010: begin // slti
            RegDst = 0;
            RegWrite = 1;
            ALUSrc = 1;
            MemWrite = 0;
            MemtoReg = 0;
            Branch = 0;
            Jump = 0;
            Jal = 0;
            Lui = 0;
            ALUOp = 2'b11;
        end

        6'b000010: begin // j
            RegDst = 1'b0; // don't care
            RegWrite = 0;
            ALUSrc = 1'b0; // don't care
            MemWrite = 0;
            MemtoReg = 1'b0; // don't care
            Branch = 0;
            Jump = 1;
            Jal = 0;
            Lui = 0;
            ALUOp = 2'b00; // don't care
        end

        6'b000011: begin // jal
            RegDst = 1'b0; // don't care
            RegWrite = 1;
            ALUSrc = 1'b0; // don't care
            MemWrite = 0;
            MemtoReg = 1'b0; // don't care
            Branch = 0;
            Jump = 1;
            Jal = 1;
            Lui = 0;
            ALUOp = 2'b00; // don't care
        end

        6'b001111: begin
            RegDst = 0;
            RegWrite = 1;
            ALUSrc = 1'b0; // don't care
            MemWrite = 0;
            MemtoReg = 0;
            Branch = 0;
            Jump = 0;
            Jal = 0;
            Lui = 1;
            ALUOp = 2'b00; // don't care
        end
        default: begin
            RegDst = 0;
            RegWrite = 0;
            ALUSrc = 0;
            MemWrite = 0;
            MemtoReg = 0;
            Branch = 0;
            Jump = 0;
            Jal = 0;
            Lui = 0;
            ALUOp = 2'b00;
        end 
    endcase
end
    
endmodule

mips_cpu.v
`include "PC.v"
`include "instr_mem.v"
`include "reg_file.v"
`include "alu.v"
`include "data_mem.v"
`include "Control_Unit.v"
`include "ALUcontrol.v"

module mips_cpu (
    input wire clk, pc_reset
);

wire [31:0] pc_out, next_pc;
wire [31:0] instr;

wire RegWrite, RegDst, ALUSrc;
wire Branch, MemWrite, MemtoReg, Jump, Jal, Lui;
wire [1:0] ALUOp;

// alu wires
wire [31:0] SrcA, SrcB;
wire Zero;
wire [31:0] ALUResult;

// data_mem wires
wire [31:0] WriteData;
wire [31:0] ReadData;

// Intermediate wires
wire [31:0] WriteBackData;
wire [4:0] WriteReg;
wire [31:0] SignImm;
wire [31:0] PCBranch;
wire PCSrc;

control_unit control_unit (
    .op_code(instr[31:26]),
    .RegDst(RegDst),
    .RegWrite(RegWrite),
    .ALUSrc(ALUSrc),
    .MemtoReg(MemtoReg),
    .MemWrite(MemWrite),
    .Branch(Branch),
    .Jump(Jump),
    .Jal(Jal),
    .Lui(Lui),
    .ALUOp(ALUOp)
);

wire [3:0] ALUControlCode;

ALUControl ALUControl (
    .ALUOp(ALUOp),
    .funct(instr[5:0]),
    .op_code(instr[31:26]),
    .code(ALUControlCode)
);

pc PC (
    .clk(clk),
    .reset(pc_reset),
    .next_pc(next_pc),
    .pc_out(pc_out)
);

instr_mem instr_mem (
    .addr(pc_out),
    .instr(instr)
);

reg_file reg_file (
    .clk(clk),
    .we3(RegWrite),
    .ra1(instr[25:21]),
    .ra2(instr[20:16]),
    .wa3(WriteReg),
    .wd3(WriteBackData),
    .rd1(SrcA),
    .rd2(WriteData)
);

assign WriteReg = Jal ? 5'd31 :
                  (RegDst ? instr[15:11] : instr[20:16]);


alu alu (
    .a(SrcA),
    .b(SrcB),
    .alu_op(ALUControlCode),
    .zero(Zero),
    .result(ALUResult)
);

assign SrcB = ALUSrc ? SignImm : WriteData;

data_mem data_mem (
    .clk(clk),
    .write_en(MemWrite),
    .alu_result(ALUResult),
    .write_data(WriteData),
    .read_data(ReadData)
);

assign WriteBackData = Lui ? {instr[15:0], 16'b0} :
                (Jal ? pc_out + 4 :
                (MemtoReg ? ReadData : ALUResult));

assign SignImm = { {16{instr[15]}}, instr[15:0] };

assign PCSrc = Branch & ~Zero;
assign PCBranch = pc_out + (SignImm << 2);

wire [31:0] PCJump;
assign PCJump = {pc_out[31:28], instr[25:0], 2'b00};

assign next_pc = Jump ? PCJump : 
                (PCSrc ? PCBranch : pc_out + 4);



endmodule

tb_mips_cpu.v
`timescale 1ns / 1ps

module tb_MIPS_CPU;

reg clk = 0;
reg pc_reset;

mips_cpu uut (
    .clk(clk),
    .pc_reset(pc_reset)
);

// Clock generation: 10ns period
always #5 clk = ~clk;

initial begin

    $dumpfile("mips_cpu.vcd"); // VCD file to generate
    $dumpvars(0, tb_MIPS_CPU);
    // Initial reset
    pc_reset = 1;
    #10;
    pc_reset = 0;

    // Run simulation
    #200;

    $finish;
end

// Debug output
initial begin
    $monitor("Time: %t | PC: %h | Instr: %h | ALUResult: %h | WriteBackData: %h",
             $time, uut.pc_out, uut.instr, uut.ALUResult, uut.WriteBackData);
end

endmodule

mips_cpu.vcd
$date
	Mon Jun 16 14:52:52 2025
$end
$version
	Icarus Verilog
$end
$timescale
	1ps
$end
$scope module tb_MIPS_CPU $end
$var reg 1 ! clk $end
$var reg 1 " pc_reset $end
$scope module uut $end
$var wire 1 # PCSrc $end
$var wire 1 ! clk $end
$var wire 1 " pc_reset $end
$var wire 32 $ pc_out [31:0] $end
$var wire 32 % next_pc [31:0] $end
$var wire 32 & instr [31:0] $end
$var wire 1 ' Zero $end
$var wire 5 ( WriteReg [4:0] $end
$var wire 32 ) WriteData [31:0] $end
$var wire 32 * WriteBackData [31:0] $end
$var wire 32 + SrcB [31:0] $end
$var wire 32 , SrcA [31:0] $end
$var wire 32 - SignImm [31:0] $end
$var wire 1 . RegWrite $end
$var wire 1 / RegDst $end
$var wire 32 0 ReadData [31:0] $end
$var wire 32 1 PCJump [31:0] $end
$var wire 32 2 PCBranch [31:0] $end
$var wire 1 3 MemtoReg $end
$var wire 1 4 MemWrite $end
$var wire 1 5 Lui $end
$var wire 1 6 Jump $end
$var wire 1 7 Jal $end
$var wire 1 8 Branch $end
$var wire 1 9 ALUSrc $end
$var wire 32 : ALUResult [31:0] $end
$var wire 2 ; ALUOp [1:0] $end
$var wire 4 < ALUControlCode [3:0] $end
$scope module ALUControl $end
$var wire 6 = funct [5:0] $end
$var wire 6 > op_code [5:0] $end
$var wire 2 ? ALUOp [1:0] $end
$var reg 4 @ code [3:0] $end
$upscope $end
$scope module PC $end
$var wire 1 ! clk $end
$var wire 32 A next_pc [31:0] $end
$var wire 1 " reset $end
$var reg 32 B pc_out [31:0] $end
$upscope $end
$scope module alu $end
$var wire 4 C alu_op [3:0] $end
$var wire 32 D b [31:0] $end
$var wire 33 E sub_result [32:0] $end
$var wire 33 F add_result [32:0] $end
$var wire 32 G a [31:0] $end
$var reg 32 H result [31:0] $end
$var reg 1 ' zero $end
$upscope $end
$scope module control_unit $end
$var wire 6 I op_code [5:0] $end
$var reg 2 J ALUOp [1:0] $end
$var reg 1 9 ALUSrc $end
$var reg 1 8 Branch $end
$var reg 1 7 Jal $end
$var reg 1 6 Jump $end
$var reg 1 5 Lui $end
$var reg 1 4 MemWrite $end
$var reg 1 3 MemtoReg $end
$var reg 1 / RegDst $end
$var reg 1 . RegWrite $end
$upscope $end
$scope module data_mem $end
$var wire 32 K addr [31:0] $end
$var wire 32 L alu_result [31:0] $end
$var wire 1 ! clk $end
$var wire 3 M mem_op [2:0] $end
$var wire 1 4 write_en $end
$var wire 32 N write_data [31:0] $end
$var reg 32 O read_data [31:0] $end
$upscope $end
$scope module instr_mem $end
$var wire 32 P addr [31:0] $end
$var wire 32 Q instr [31:0] $end
$upscope $end
$scope module reg_file $end
$var wire 1 ! clk $end
$var wire 5 R ra1 [4:0] $end
$var wire 5 S ra2 [4:0] $end
$var wire 5 T wa3 [4:0] $end
$var wire 32 U wd3 [31:0] $end
$var wire 1 . we3 $end
$var wire 32 V rd2 [31:0] $end
$var wire 32 W rd1 [31:0] $end
$upscope $end
$upscope $end
$upscope $end
$enddefinitions $end
$comment Show the parameter values. $end
$dumpall
$end
#0
$dumpvars
bx W
bx V
bx U
b11 T
b10 S
b1 R
b1000100001100000100000 Q
b0 P
b0 O
bx N
bz M
bx L
bx K
b10 J
b0 I
bx H
bx G
bx F
bx E
bx D
b10 C
b0 B
b100 A
b10 @
b10 ?
b0 >
b100000 =
b10 <
b10 ;
bx :
09
08
07
06
05
04
03
b110000010000000 2
b100010000110000010000000 1
b0 0
1/
1.
b1100000100000 -
bx ,
bx +
bx *
bx )
b11 (
x'
b1000100001100000100000 &
b100 %
b0 $
0#
1"
0!
$end
#5000
1!
#10000
0!
0"
#15000
b100 (
b100 T
b110 <
b110 @
b110 C
b1100001001000000010001000 1
b10000000100010 -
b1 S
b11 R
b100010 =
b1000 %
b1000 A
b11000010010000000100010 &
b11000010010000000100010 Q
b1000000010001100 2
b100 $
b100 B
b100 P
1!
#20000
0!
#25000
b0 *
b0 U
b101 (
b101 T
1'
b0 K
b0 :
b0 H
b0 L
b1010 F
b111111111111111111111111111110110 E
b1010 +
b1010 D
b0 ,
b0 G
b0 W
b0 <
b0 @
b0 C
b0 ;
b0 ?
b0 J
19
0/
b101000000000000101000 1
b1010 -
b101 S
b0 R
b1000 >
b1010 =
b1000 I
b1100 %
b1100 A
b100000000001010000000000001010 &
b100000000001010000000000001010 Q
b110000 2
b1000 $
b1000 B
b1000 P
1!
#30000
0!
#35000
b110 (
b110 T
b100 F
b111111111111111111111111111111100 E
b100 +
b100 D
13
b10100110000000000000010000 1
b100 -
b110 S
b101 R
b100011 >
b100 =
b100011 I
b10000 %
b10000 A
b10001100101001100000000000000100 &
b10001100101001100000000000000100 Q
bx )
bx N
bx V
b11100 2
b1100 $
b1100 B
b1100 P
1!
#40000
0!
#45000
b1000 F
b111111111111111111111111111111000 E
b1000 +
b1000 D
03
14
0.
b10100110000000000000100000 1
b1000 -
b101011 >
b1000 =
b101011 I
b10100 %
b10100 A
b10101100101001100000000000001000 &
b10101100101001100000000000001000 Q
b0 )
b0 N
b0 V
b110000 2
b10000 $
b10000 B
b10000 P
1!
#50000
0!
#55000
bx *
bx U
x#
b10 (
b10 T
x'
bx K
bx :
bx H
bx L
bx +
bx D
bx )
bx N
bx V
bx E
bx F
bx ,
bx G
bx W
b110 <
b110 @
b110 C
b1 ;
b1 ?
b1 J
18
04
09
b100010000000000000001000 1
b10 -
b10 S
b1 R
b100 >
b10 =
b100 I
b11x00 %
b11x00 A
b10000001000100000000000000010 &
b10000001000100000000000000010 Q
b11100 2
b10100 $
b10100 B
b10100 P
1!
#60000
0!
#65000
bx (
bx T
0#
b0 <
b0 @
b0 C
b0 ;
b0 ?
b0 J
08
b0xxxxxxxxxxxxxxxxxxxxxxxxxx00 1
bx -
bx S
bx R
bx >
bx =
bx I
bx %
bx A
bx &
bx Q
bx 2
b11x00 $
b11x00 B
b11x00 P
1!
#70000
0!
#75000
bx00 1
bx $
bx B
bx P
1!
